NavEcho/__init__.py
NavEcho/logger.py
NavEcho-0.81.0.dist-info/METADATA
NavEcho-0.81.0.dist-info/WHEEL
NavEcho-0.81.0.dist-info/entry_points.txt
NavEcho-0.81.0.dist-info/top_level.txt
NavEcho-0.81.0.dist-info/RECORD
