Metadata-Version: 2.1
Name: NavEcho
Version: 0.81.0
Summary: A standalone library for collecting and logging errors from external applications.
Author: aayush chaudhary
Author-email: aayush.chaudhary@navikenz.com
Classifier: Programming Language :: Python :: 3
Classifier: License :: OSI Approved :: MIT License
Classifier: Operating System :: OS Independent
Requires-Python: >=3.6
Requires-Dist: requests
